setup.py
litepygraphql.egg-info/PKG-INFO
litepygraphql.egg-info/SOURCES.txt
litepygraphql.egg-info/dependency_links.txt
litepygraphql.egg-info/requires.txt
litepygraphql.egg-info/top_level.txt
pygraphql/__init__.py