Metadata-Version: 2.1
Name: litepygraphql
Version: 1.2.0
Summary: graphql Python.
Author: Pain
Author-email: benjaminrodriguezshhh@proton.me
